README.md
setup.cfg
setup.py
fdjangodog/__init__.py
fdjangodog/middleware.py
fdjangodog.egg-info/PKG-INFO
fdjangodog.egg-info/SOURCES.txt
fdjangodog.egg-info/dependency_links.txt
fdjangodog.egg-info/requires.txt
fdjangodog.egg-info/top_level.txt