Metadata-Version: 1.1
Name: fdjangodog
Version: 0.5.1
Summary: Simple Django middleware for submitting timings and exceptions to Datadog.
Home-page: https://github.com/tom-dalton-fanduel/fdjangodog
Author: Tom Dalton
Author-email: tom.dalton@fanduel.com
License: BSD
Platform: UNKNOWN
Classifier: Programming Language :: Python
Classifier: Programming Language :: Python :: 2
Classifier: Programming Language :: Python :: 2.7
Classifier: Programming Language :: Python :: 3
Classifier: Programming Language :: Python :: 3.4
Classifier: Programming Language :: Python :: 3.5
Classifier: Programming Language :: Python :: 3.6
